<?xml version="1.0" encoding="UTF-8" standalone="no"?><carnet_entrenador><id>5</id><fecha_exp>03 02 2025</fecha_exp><nombre_entrenador>luis</nombre_entrenador><hoy>03 02 2025</hoy><entrenador><nacionalidad_entrenador>España</nacionalidad_entrenador></entrenador><Torneos><torneo><nombre>Ventolera</nombre><region>0</region><victoria>true</victoria><Combates><combate><id>13</id><fecha>2025-02-03</fecha><victoria>true</victoria></combate><combate><id>14</id><fecha>2025-02-03</fecha><victoria>false</victoria></combate><combate><id>15</id><fecha>2025-02-03</fecha><victoria>true</victoria></combate></Combates></torneo><torneo><nombre>Ferrero</nombre><region>B</region><victoria>No Finalizado</victoria><Combates><combate><id>16</id><fecha>2025-02-03</fecha><victoria>No participado</victoria></combate><combate><id>17</id><fecha>2025-02-03</fecha><victoria>No participado</victoria></combate><combate><id>18</id><fecha>2025-02-03</fecha><victoria>No participado</victoria></combate></Combates></torneo><torneo><nombre>Corolla</nombre><region>q</region><victoria>No Finalizado</victoria><Combates><combate><id>19</id><fecha>2025-02-03</fecha><victoria>No participado</victoria></combate><combate><id>20</id><fecha>2025-02-03</fecha><victoria>No participado</victoria></combate><combate><id>21</id><fecha>2025-02-03</fecha><victoria>No participado</victoria></combate></Combates></torneo></Torneos></carnet_entrenador>